AUTHORS.rst
CHANGES.rst
LICENSE
README.rst
setup.cfg
setup.py
pytest_selenium_enhancer/__init__.py
pytest_selenium_enhancer/custom_expected_conditions.py
pytest_selenium_enhancer/custom_wait.py
pytest_selenium_enhancer/plugin.py
pytest_selenium_enhancer/pytest_selenium_enhancer.py
pytest_selenium_enhancer.egg-info/PKG-INFO
pytest_selenium_enhancer.egg-info/SOURCES.txt
pytest_selenium_enhancer.egg-info/dependency_links.txt
pytest_selenium_enhancer.egg-info/entry_points.txt
pytest_selenium_enhancer.egg-info/requires.txt
pytest_selenium_enhancer.egg-info/top_level.txt