Metadata-Version: 1.1
Name: pytest-selenium-enhancer
Version: 1.6.2
Summary: pytest plugin for Selenium
Home-page: https://github.com/popescunsergiu/pytest-selenium-enhancer
Author: Sergiu Popescu
Author-email: popescunsergiu@gmail.com
License: MIT License
Download-URL: https://github.com/popescunsergiu/pytest-selenium-enhancer/archive/v1.6.1.tar.gz
Keywords: py.test pytest qa
Platform: UNKNOWN
Classifier: Development Status :: 5 - Production/Stable
Classifier: Framework :: Pytest
Classifier: Intended Audience :: Developers
Classifier: License :: OSI Approved :: MIT License
Classifier: Operating System :: OS Independent
Classifier: Topic :: Software Development :: Quality Assurance
Classifier: Topic :: Software Development :: Testing
Classifier: Topic :: Utilities
Classifier: Programming Language :: Python
Classifier: Programming Language :: Python :: 3
